{
    "social": {
        "consistently voted for": [
            "equal gay rights",
            "laws to promote equality and human rights"
        ],
        "voted for": [
            "allowing marriage between two people of same sex"
        ]
    },
    "welfare": {
        "voted against": [
            "reducing housing benefit for social tenants deemed to have excess bedrooms (which Labour describe as the "
        ]
    },
    "transport": {
        "consistently voted against": [
            "higher taxes on plane tickets"
        ]
    },
    "misc": {
        "voted against": [
            "capping civil service redundancy payments"
        ],
        "consistently voted for": [
            "restrictions on fees charged to tenants by letting agents"
        ]
    },
    "environment": {
        "has never voted on": [
            "new high speed rail infrastructure"
        ],
        "almost always voted for": [
            "measures to prevent climate change"
        ],
        "voted for": [
            "financial incentives for low carbon emission electricity generation methods"
        ],
        "consistently voted against": [
            "higher taxes on plane tickets"
        ]
    },
    "education": {
        "voted against": [
            "university tuition fees"
        ]
    },
    "home": {
        "consistently voted against": [
            "a stricter asylum system"
        ]
    },
    "health": {
        "voted against": [
            "reforming the NHS so GPs buy services on behalf of their patients"
        ]
    },
    "taxation": {
        "voted against": [
            "increasing the rate of VAT"
        ],
        "generally voted against": [
            "raising the threshold at which people start to pay income tax"
        ],
        "consistently voted against": [
            "higher taxes on plane tickets"
        ],
        "consistently voted for": [
            "higher taxes on banks"
        ]
    },
    "foreignpolicy": {
        "consistently voted for": [
            "UK membership of the EU"
        ],
        "generally voted for": [
            "more EU integration"
        ],
        "voted a mixture of for and against": [
            "a right to remain for EU nationals already in living in the UK"
        ]
    },
    "reform": {
        "has never voted on": [
            "fewer MPs in the House of Commons",
            "local councils keeping money raised from taxes on business premises in their areas",
            "a more proportional system for electing MPs"
        ],
        "generally voted for": [
            "transferring more powers to the Scottish Parliament",
            "transferring more powers to the Senedd/Welsh Parliament"
        ],
        "consistently voted against": [
            "reducing central government funding of local government"
        ],
        "voted against": [
            "an equal number of electors per parliamentary constituency"
        ],
        "voted for": [
            "more powers for local councils"
        ]
    },
    "business": {
        "has never voted on": [
            "new high speed rail infrastructure"
        ],
        "voted a mixture of for and against": [
            "measures to reduce tax avoidance"
        ]
    }
}